LICENSE
MANIFEST.in
README.md
setup.cfg
setup.py
jrdbparser/__init__.py
jrdbparser/jrdbparser.py
jrdbparser/writer.py
jrdbparser.egg-info/PKG-INFO
jrdbparser.egg-info/SOURCES.txt
jrdbparser.egg-info/dependency_links.txt
jrdbparser.egg-info/top_level.txt
jrdbparser/schema/__init__.py
jrdbparser/schema/kab.py
tests/__init__.py
tests/test_kabparser.py