Metadata-Version: 1.0
Name: jrdbparser
Version: 0.0.4
Summary: Parser for JRDB data
Home-page: https://github.com/otomarukanta/jrdbparser
Author: Kanta Kuramoto
Author-email: kanta208@gmail.com
License:                                  Apache License
